terrakit/__init__.py
terrakit/__main__.py
terrakit/_version.py
terrakit/chip/__init__.py
terrakit/chip/tiling.py
terrakit/download/__init__.py
terrakit/download/collections.json
terrakit/download/connector.py
terrakit/download/connector_template.py
terrakit/download/data_connectors/__init__.py
terrakit/download/data_connectors/connector_template.py
terrakit/download/data_connectors/ibmresearch_stac.py
terrakit/download/data_connectors/nasa_earthdata.py
terrakit/download/data_connectors/sentinel_aws.py
terrakit/download/data_connectors/sentinelhub.py
terrakit/download/data_connectors/theweathercompany.py
terrakit/download/download_data.py
terrakit/download/geodata_utils.py
terrakit/download/raster_file_reader.py
terrakit/download/transformations/__init__.py
terrakit/download/transformations/download_transformation_template.py
terrakit/download/transformations/impute_nans_xarray.py
terrakit/download/transformations/scale_data_xarray.py
terrakit/general_utils/__init__.py
terrakit/general_utils/curation_metadata.py
terrakit/general_utils/defaults.py
terrakit/general_utils/exceptions.py
terrakit/general_utils/geospatial_util.py
terrakit/general_utils/labels_downloader.py
terrakit/general_utils/plotting.py
terrakit/general_utils/rest.py
terrakit/general_utils/statistics.py
terrakit/store/__init__.py
terrakit/store/taco.py
terrakit/terrakit.py
terrakit/transform/__init__.py
terrakit/transform/labels.py
terrakit/upload/__init__.py
terrakit/validate/__init__.py
terrakit/validate/data_connector.py
terrakit/validate/download_model.py
terrakit/validate/helpers.py
terrakit/validate/labels_model.py
terrakit/validate/pipeline_model.py
terrakit/validate/tiling_model.py
terrakit-0.1.3.dist-info/WHEEL
terrakit-0.1.3.dist-info/entry_points.txt
terrakit-0.1.3.dist-info/METADATA
terrakit-0.1.3.dist-info/RECORD
