Metadata-Version: 2.3
Name: terrakit
Version: 0.1.3
Summary: A Python package for finding and getting geospatial data.
Author: Blair Edwards, Rosie Lickorish, Leonardo Pondian Tizzei, Fred Ochieng Otieno, Beldine Moturi, Catherine Wanjiru, Benedikt Blumenstiel, Brian Ogolla
Author-email: Blair Edwards <bedwards@uk.ibm.com>
Requires-Dist: aiohttp>=3.12.15
Requires-Dist: contextily>=1.6.2
Requires-Dist: boto3
Requires-Dist: dask==2025.7.0
Requires-Dist: folium>=0.20.0
Requires-Dist: huggingface-hub
Requires-Dist: geojson>=3.2.0
Requires-Dist: geopandas>=1.1.1
Requires-Dist: joblib==1.5.2
Requires-Dist: jsonargparse>=4.40.2
Requires-Dist: nest-asyncio>=1.6.0
Requires-Dist: numpy>=1.26.4
Requires-Dist: pydantic>=2.11.7
Requires-Dist: pystac-client==0.9.0
Requires-Dist: python-dotenv>=1.1.1
Requires-Dist: rasterio==1.4.3
Requires-Dist: rioxarray[interp]==0.19.0
Requires-Dist: s3fs
Requires-Dist: scikit-learn>=1.7.1
Requires-Dist: sentinelhub==3.11.1
Requires-Dist: shapely>=2.1.1
Requires-Dist: stackstac==0.5.1
Requires-Dist: tacoreader==0.5.6
Requires-Dist: tacotoolbox==0.5.2
Requires-Dist: tqdm==4.67.1
Requires-Dist: xarray>=2023.1.0
Requires-Dist: urllib3==2.5.0
Requires-Dist: h5netcdf>=1.7.3
Requires-Python: >=3.10
Project-URL: Documentation, https://terrastackai.github.io/terrakit/
Project-URL: Issues, https://github.com/terrastackai/terrakit/issues
Project-URL: Source, https://github.com/terrastackai/terrakit
